rocketdoo/__init__.py
rocketdoo/cli.py
rocketdoo/config.py
rocketdoo/delete_identifiers.py
rocketdoo/deploy_cli.py
rocketdoo/docker_cli.py
rocketdoo/init_project.py
rocketdoo/main.py
rocketdoo/project_info.py
rocketdoo/rocketdoo.py
rocketdoo/scaffold.py
rocketdoo/welcome.py
rocketdoo/core/__init__.py
rocketdoo/core/config_loader.py
rocketdoo/core/edition_setup.py
rocketdoo/core/generator.py
rocketdoo/core/gitman_config.py
rocketdoo/core/module_scanner.py
rocketdoo/core/port_validation.py
rocketdoo/core/ssh_manager.py
rocketdoo/core/utils.py
rocketdoo/core/deploy/__init__.py
rocketdoo/core/deploy/base.py
rocketdoo/core/deploy/config_manager.py
rocketdoo/core/deploy/module_packager.py
rocketdoo/core/deploy/odoo_sh.py
rocketdoo/core/deploy/vps.py
rocketdoo/templates/Dockerfile.jinja
rocketdoo/templates/docker-compose.yaml.jinja
rocketdoo/templates/install_dependencies.sh
rocketdoo/templates/odoo_pg_pass
rocketdoo/templates/.devcontainer/devcontainer.json
rocketdoo/templates/.devcontainer/docker-compose.yaml
rocketdoo/templates/.vscode/launch.json
rocketdoo/templates/.vscode/launch.json.jinja
rocketdoo/templates/.vscode/settings.json
rocketdoo/templates/addons/.gitkeep
rocketdoo/templates/config/odoo.conf
rocketdoo/templates/config/odoo.conf.jinja
rocketdoo/templates/deploy/.deployignore
rocketdoo/templates/deploy/deploy.yaml
rocketdoo/templates/deploy/deploy.yaml.jinja
rocketdoo-2.2.4.dist-info/licenses/LICENSE
rocketdoo-2.2.4.dist-info/METADATA
rocketdoo-2.2.4.dist-info/WHEEL
rocketdoo-2.2.4.dist-info/entry_points.txt
rocketdoo-2.2.4.dist-info/top_level.txt
rocketdoo-2.2.4.dist-info/RECORD
