Metadata-Version: 2.4
Name: rocketdoo
Version: 2.2.4
Summary: Framework for creating Odoo development environments with Docker and custom templates.
Author-email: Horacio Montaño <horaciomontano@hdmsoft.com.ar>
License: GNU LESSER GENERAL PUBLIC LICENSE
Requires-Python: >=3.10
License-File: LICENSE
Requires-Dist: click>=8.1.3
Requires-Dist: copier>=9.2.0
Requires-Dist: jinja2>=3.1.2
Requires-Dist: pyyaml>=6.0
Requires-Dist: rich>=13.0
Requires-Dist: pyfiglet>=1.0
Requires-Dist: questionary>=1.10.0
Dynamic: license-file
